ai_core_sdk/__init__.py
ai_core_sdk/ai_core_v2_client.py
ai_core_sdk/cli.py
ai_core_sdk/content_cli_main.py
ai_core_sdk/credentials.py
ai_core_sdk/exception.py
ai_core_sdk/content/README.md
ai_core_sdk/content/__init__.py
ai_core_sdk/content/cli.py
ai_core_sdk/content/content_package.py
ai_core_sdk/content/print_utils.py
ai_core_sdk/content/workflow.py
ai_core_sdk/helpers/__init__.py
ai_core_sdk/helpers/constants.py
ai_core_sdk/helpers/logging.py
ai_core_sdk/models/__init__.py
ai_core_sdk/models/application.py
ai_core_sdk/models/application_query_response.py
ai_core_sdk/models/application_resource_sync_status.py
ai_core_sdk/models/application_source.py
ai_core_sdk/models/application_status.py
ai_core_sdk/models/base_models.py
ai_core_sdk/models/docker_registry_secret.py
ai_core_sdk/models/docker_registry_secret_query_response.py
ai_core_sdk/models/kpi.py
ai_core_sdk/models/object_store_secret.py
ai_core_sdk/models/object_store_secret_query_response.py
ai_core_sdk/models/repository.py
ai_core_sdk/models/repository_query_response.py
ai_core_sdk/models/repository_status.py
ai_core_sdk/models/resource_group.py
ai_core_sdk/models/resource_group_query_response.py
ai_core_sdk/models/resource_group_status.py
ai_core_sdk/models/secret.py
ai_core_sdk/models/secret_query_response.py
ai_core_sdk/resource_clients/__init__.py
ai_core_sdk/resource_clients/applications_client.py
ai_core_sdk/resource_clients/docker_registry_secrets_client.py
ai_core_sdk/resource_clients/internal_rest_client.py
ai_core_sdk/resource_clients/kpi_client.py
ai_core_sdk/resource_clients/metrics_client.py
ai_core_sdk/resource_clients/object_store_secrets_client.py
ai_core_sdk/resource_clients/repositories_client.py
ai_core_sdk/resource_clients/secrets_client.py
ai_core_sdk/tracking/__init__.py
ai_core_sdk/tracking/tracking.py
ai_core_sdk-2.4.14.data/data/docs/ai_core_sdk.ai_core_v2_client.html
ai_core_sdk-2.4.14.data/data/docs/ai_core_sdk.cli.html
ai_core_sdk-2.4.14.dist-info/LICENSE
ai_core_sdk-2.4.14.dist-info/METADATA
ai_core_sdk-2.4.14.dist-info/WHEEL
ai_core_sdk-2.4.14.dist-info/entry_points.txt
ai_core_sdk-2.4.14.dist-info/top_level.txt
ai_core_sdk-2.4.14.dist-info/RECORD
