Metadata-Version: 2.1
Name: ai-core-sdk
Version: 2.4.14
Summary: SAP AI Core SDK
Home-page: https://www.sap.com/
Author: SAP SE
License: SAP DEVELOPER LICENSE AGREEMENT
Download-URL: https://pypi.python.org/pypi/ai-core-sdk
Keywords: SAP AI Core SDK,SAP AI Core API,SAP AI Core
Platform: Windows
Platform: Linux
Platform: Mac OS-X
Platform: Unix
Classifier: Development Status :: 5 - Production/Stable
Classifier: Intended Audience :: Developers
Classifier: Intended Audience :: End Users/Desktop
Classifier: Intended Audience :: Financial and Insurance Industry
Classifier: Intended Audience :: Healthcare Industry
Classifier: Intended Audience :: Information Technology
Classifier: Intended Audience :: Legal Industry
Classifier: Intended Audience :: Manufacturing
Classifier: Intended Audience :: Science/Research
Classifier: License :: Other/Proprietary License
Classifier: Operating System :: MacOS :: MacOS X
Classifier: Operating System :: Microsoft :: Windows :: Windows 10
Classifier: Operating System :: Microsoft :: Windows :: Windows 7
Classifier: Operating System :: Microsoft :: Windows :: Windows 8
Classifier: Operating System :: Microsoft :: Windows :: Windows 8.1
Classifier: Operating System :: Microsoft :: Windows :: Windows Server 2008
Classifier: Operating System :: POSIX :: Linux
Classifier: Programming Language :: Python
Classifier: Programming Language :: Python :: 3
Classifier: Programming Language :: Python :: 3.8
Classifier: Programming Language :: Python :: 3.9
Classifier: Programming Language :: Python :: 3.10
Classifier: Programming Language :: Python :: 3.11
Classifier: Programming Language :: Python :: 3.12
Classifier: Topic :: Database
Classifier: Topic :: Software Development :: Libraries :: Python Modules
Requires-Python: >=3.7
Requires-Dist: ai-api-client-sdk (==2.4.0)
Requires-Dist: click (~=8.1)
Provides-Extra: aicore-content
Requires-Dist: sap-ai-core-metaflow[kubernetes] (~=1.1.21) ; extra == 'aicore-content'
Requires-Dist: awscli (~=1.31) ; extra == 'aicore-content'
Requires-Dist: python-dotenv (~=1.0.0) ; extra == 'aicore-content'
Provides-Extra: all
Requires-Dist: sap-ai-core-metaflow[kubernetes] (~=1.1.21) ; extra == 'all'
Requires-Dist: awscli (~=1.31) ; extra == 'all'
Requires-Dist: python-dotenv (~=1.0.0) ; extra == 'all'
